{
    "Bracket": "Bracket field",
    "Schedule": "Schedule field",
    "comm1": "TestDunedin",
    "comm1Pronoun": "he/him",
    "comm1Pronounx": "",
    "comm1x": "",
    "comm2": "TestAuckland",
    "comm2Pronoun": "she/her",
    "comm2Pronounx": "",
    "comm2x": "",
    "dTimeText": "Be right back!",
    "game": "SSBU",
    "gf2p1": "",
    "gf2p1s": "",
    "gf2p2": "",
    "gf2p2s": "",
    "gfp1": "",
    "gfp1s": "",
    "gfp2": "",
    "gfp2s": "",
    "int0": "Int0",
    "int1": "Int1",
    "int2": "Int2",
    "int3": "Int3",
    "lfp1": "",
    "lfp1s": "",
    "lfp2": "",
    "lfp2s": "",
    "lq1p1": "",
    "lq1p1s": "",
    "lq1p2": "",
    "lq1p2s": "",
    "lq2p1": "",
    "lq2p1s": "",
    "lq2p2": "",
    "lq2p2s": "",
    "lsp1": "",
    "lsp1s": "",
    "lsp2": "",
    "lsp2s": "",
    "ltop81p1": "",
    "ltop81p1s": "",
    "ltop81p2": "",
    "ltop81p2s": "",
    "ltop82p1": "",
    "ltop82p1s": "",
    "ltop82p2": "",
    "ltop82p2s": "",
    "p1Loserx": "0",
    "p1Name": "TestChristchurch",
    "p1Namex": "",
    "p1Pronoun": "they/them",
    "p1Pronounx": "",
    "p1Region": "",
    "p1Scorex": "0",
    "p1Team": "Christchurch",
    "p1Teamx": "",
    "p2Loserx": "0",
    "p2Name": "TestWellington",
    "p2Namex": "",
    "p2Pronoun": "she/her",
    "p2Pronounx": "",
    "p2Region": "",
    "p2Scorex": "0",
    "p2Team": "Wellington",
    "p2Teamx": "",
    "round": "",
    "s1p1Score": "0",
    "s1p2Score": "0",
    "s2p1Score": "0",
    "s2p2Score": "0",
    "s3p1Score": "0",
    "s3p2Score": "0",
    "s4p1Score": "0",
    "s4p2Score": "0",
    "s5p1Score": "0",
    "s5p2Score": "0",
    "showTimer": "1",
    "timerLength": "3:00",
    "timerStart": "0",
    "timestamp": "1642126255",
    "wfp1": "",
    "wfp1s": "",
    "wfp2": "",
    "wfp2s": "",
    "ws1p1": "",
    "ws1p1s": "",
    "ws1p2": "",
    "ws1p2s": "",
    "ws2p1": "",
    "ws2p1s": "",
    "ws2p2": "",
    "ws2p2s": ""
}
